{"errors":[],"warnings":[],"namedChunkGroups":{"app":{"chunks":[8,1,0,2],"assets":["webpack-runtime-ebb53d4f70dad61d9350.js","webpack-runtime-ebb53d4f70dad61d9350.js.map","styles.c395d1de6582d9cf8d21.css","styles-1df6008a43e9fc5458f1.js","styles-1df6008a43e9fc5458f1.js.map","commons-97759cdab8ae5805e34d.js","commons-97759cdab8ae5805e34d.js.map","app-4d663792122df2492420.js","app-4d663792122df2492420.js.map"],"children":{},"childAssets":{}},"component---src-templates-blog-js":{"chunks":[1,0,7],"assets":["styles.c395d1de6582d9cf8d21.css","styles-1df6008a43e9fc5458f1.js","styles-1df6008a43e9fc5458f1.js.map","commons-97759cdab8ae5805e34d.js","commons-97759cdab8ae5805e34d.js.map","component---src-templates-blog-js-0b5d61d4e1e0239ee5b0.js","component---src-templates-blog-js-0b5d61d4e1e0239ee5b0.js.map"],"children":{},"childAssets":{}},"component---src-pages-404-js":{"chunks":[1,0,3],"assets":["styles.c395d1de6582d9cf8d21.css","styles-1df6008a43e9fc5458f1.js","styles-1df6008a43e9fc5458f1.js.map","commons-97759cdab8ae5805e34d.js","commons-97759cdab8ae5805e34d.js.map","component---src-pages-404-js-4c9d1a3e15961d3c589c.js","component---src-pages-404-js-4c9d1a3e15961d3c589c.js.map"],"children":{},"childAssets":{}},"component---src-pages-index-js":{"chunks":[1,0,4],"assets":["styles.c395d1de6582d9cf8d21.css","styles-1df6008a43e9fc5458f1.js","styles-1df6008a43e9fc5458f1.js.map","commons-97759cdab8ae5805e34d.js","commons-97759cdab8ae5805e34d.js.map","component---src-pages-index-js-7d2d9bfde7f8d34638c9.js","component---src-pages-index-js-7d2d9bfde7f8d34638c9.js.map"],"children":{},"childAssets":{}},"component---src-pages-info-js":{"chunks":[1,0,5],"assets":["styles.c395d1de6582d9cf8d21.css","styles-1df6008a43e9fc5458f1.js","styles-1df6008a43e9fc5458f1.js.map","commons-97759cdab8ae5805e34d.js","commons-97759cdab8ae5805e34d.js.map","component---src-pages-info-js-50744d08e9b39532200d.js","component---src-pages-info-js-50744d08e9b39532200d.js.map"],"children":{},"childAssets":{}},"component---src-pages-menu-js":{"chunks":[1,0,6],"assets":["styles.c395d1de6582d9cf8d21.css","styles-1df6008a43e9fc5458f1.js","styles-1df6008a43e9fc5458f1.js.map","commons-97759cdab8ae5805e34d.js","commons-97759cdab8ae5805e34d.js.map","component---src-pages-menu-js-b9cd51185e071e0c41b5.js","component---src-pages-menu-js-b9cd51185e071e0c41b5.js.map"],"children":{},"childAssets":{}}},"assetsByChunkName":{"app":["webpack-runtime-ebb53d4f70dad61d9350.js","styles.c395d1de6582d9cf8d21.css","styles-1df6008a43e9fc5458f1.js","commons-97759cdab8ae5805e34d.js","app-4d663792122df2492420.js"],"component---src-templates-blog-js":["styles.c395d1de6582d9cf8d21.css","styles-1df6008a43e9fc5458f1.js","commons-97759cdab8ae5805e34d.js","component---src-templates-blog-js-0b5d61d4e1e0239ee5b0.js"],"component---src-pages-404-js":["styles.c395d1de6582d9cf8d21.css","styles-1df6008a43e9fc5458f1.js","commons-97759cdab8ae5805e34d.js","component---src-pages-404-js-4c9d1a3e15961d3c589c.js"],"component---src-pages-index-js":["styles.c395d1de6582d9cf8d21.css","styles-1df6008a43e9fc5458f1.js","commons-97759cdab8ae5805e34d.js","component---src-pages-index-js-7d2d9bfde7f8d34638c9.js"],"component---src-pages-info-js":["styles.c395d1de6582d9cf8d21.css","styles-1df6008a43e9fc5458f1.js","commons-97759cdab8ae5805e34d.js","component---src-pages-info-js-50744d08e9b39532200d.js"],"component---src-pages-menu-js":["styles.c395d1de6582d9cf8d21.css","styles-1df6008a43e9fc5458f1.js","commons-97759cdab8ae5805e34d.js","component---src-pages-menu-js-b9cd51185e071e0c41b5.js"]}}